envypy/__init__.py
envypy/database.py
envypy-0.0.6.dist-info/METADATA
envypy-0.0.6.dist-info/WHEEL
envypy-0.0.6.dist-info/licenses/LICENSE
envypy-0.0.6.dist-info/RECORD
