Metadata-Version: 2.4
Name: envypy
Version: 0.0.6
Summary: Envybase python sdk
Project-URL: Homepage, https://github.com/orbical-dev/envybase
Project-URL: Issues, https://github.com/pypa/orbical-dev/envybase/issues
Author-email: Zachary Jones <zacharyj@orbical.dev>
License-Expression: MIT
License-File: LICENSE
Classifier: Operating System :: OS Independent
Classifier: Programming Language :: Python :: 3
Requires-Python: >=3.9
